UC_Quantum_Lab/__init__.py
UC_Quantum_Lab/_src.py
UC_Quantum_Lab/commands.py
UC_Quantum_Lab/layout.py
UC_Quantum_tools-0.1.9.dist-info/LICENSE
UC_Quantum_tools-0.1.9.dist-info/METADATA
UC_Quantum_tools-0.1.9.dist-info/WHEEL
UC_Quantum_tools-0.1.9.dist-info/top_level.txt
UC_Quantum_tools-0.1.9.dist-info/RECORD
